{
  "orders":[
    {
      "id": 1,
      "title": "任务1",
      "desc": "多行文字超出长度省略，内容文字超出长度省略，内容文字超出长度省略，内容文字超出长度省略，内容文字超出长度省略",
      "more_infos": "",
      "status": "finish"
    },
    {
      "id": 2,
      "title": "任务2",
      "desc": "多行文字超出长度省略，内容文字超出长度省略，内容文字超出长度省略，内容文字超出长度省略，内容文字超出长度省略",
      "more_infos": "",
      "status": "finish"
    },
    {
      "id": 3,
      "title": "任务3",
      "desc": "多行文字超出长度省略，内容文字超出长度省略，内容文字超出长度省略，内容文字超出长度省略，内容文字超出长度省略",
      "more_infos": "",
      "status": "finish"
    },
    {
      "id": 4,
      "title": "任务4",
      "desc": "多行文字超出长度省略，内容文字超出长度省略，内容文字超出长度省略，内容文字超出长度省略，内容文字超出长度省略",
      "more_infos": "",
      "status": "finish"
    },
    {
      "id": 5,
      "title": "任务5",
      "desc": "多行文字超出长度省略，内容文字超出长度省略，内容文字超出长度省略，内容文字超出长度省略，内容文字超出长度省略",
      "more_infos": "",
      "status": "finish"
    }
  ],
  "status":[{
    "finish":"已结算"
  }],
  "info":"已结算订单"
}